setup.py
ZoomLinkMap.egg-info/PKG-INFO
ZoomLinkMap.egg-info/SOURCES.txt
ZoomLinkMap.egg-info/dependency_links.txt
ZoomLinkMap.egg-info/top_level.txt
bin/zoomLinkMap
zoomlinkmap/__init__.py
zoomlinkmap/linkMapFile.py