Metadata-Version: 1.0
Name: ZoomLinkMap
Version: 0.1.1
Summary: a tool to analisy the link map file that is genered by clang, to analisy your app's content
Home-page: https://github.com/yishuiliunian/ZoomLinkMap
Author: yishuiliunian@gmail.com
Author-email: yishuiliunian@gmail.com
License: MIT License
Keywords: Link Map File,analisy
Platform: any
